verilog/0_skew_Verification_AI/dff_sync.v
module dff_sync (
	input clk,
	input rst,
	input d,
	output reg q
);

	always @(posedge clk or posedge rst) begin
		if (rst)
			q <= 0;
		else
			q <= d;
	end
endmodule

verilog/0_skew_Verification_AI/tb_dff_sync.v
`timescale 1ns/1ps

module tb_skew_sim;

	reg clk_main = 0;
	reg clk_skewed = 0;
	reg rst = 1;
	reg d = 0;
	wire q_main, q_skewed;

	//clock generation (10ns period)
	always #5 clk_main = ~clk_main;

	//introduce skew (3ns delay)
	always @(clk_main) begin
		#3 clk_skewed = clk_main;
	end

	// Instantiate D-FF
	dff_sync dff1 (.clk(clk_main), .rst(rst), .d(d), .q(q_main));
	dff_sync dff2 (.clk(clk_skewed), .rst(rst), .d(d), .q(q_skewed));

	initial begin

	$dumpfile("gtk_dff_skew_sim.vcd");
	$dumpvars(0, tb_skew_sim);
	$monitor("At time = %t, d = %d", $time, d);

	#12 rst = 0; // release reset after few cycles
	#10 d = 1;
	#10 d = 0;
	#10 d = 1;
	#10 d = 0;

	#50 $finish;
	end
endmodule

verilog/0_skew_Verification_AI/gtk_dff_skew_sim.vcd
$date
	Sat May 10 02:54:44 2025
$end
$version
	Icarus Verilog
$end
$timescale
	1ps
$end
$scope module tb_skew_sim $end
$var wire 1 ! q_skewed $end
$var wire 1 " q_main $end
$var reg 1 # clk_main $end
$var reg 1 $ clk_skewed $end
$var reg 1 % d $end
$var reg 1 & rst $end
$scope module dff1 $end
$var wire 1 # clk $end
$var wire 1 % d $end
$var wire 1 & rst $end
$var reg 1 " q $end
$upscope $end
$scope module dff2 $end
$var wire 1 $ clk $end
$var wire 1 % d $end
$var wire 1 & rst $end
$var reg 1 ! q $end
$upscope $end
$upscope $end
$enddefinitions $end
#0
$dumpvars
1&
0%
0$
0#
0"
0!
$end
#5000
1#
#8000
1$
#10000
0#
#12000
0&
#13000
0$
#15000
1#
#18000
1$
#20000
0#
#22000
1%
#23000
0$
#25000
1"
1#
#28000
1!
1$
#30000
0#
#32000
0%
#33000
0$
#35000
0"
1#
#38000
0!
1$
#40000
0#
#42000
1%
#43000
0$
#45000
1"
1#
#48000
1!
1$
#50000
0#
#52000
0%
#53000
0$
#55000
0"
1#
#58000
0!
1$
